pyarmor/cli/core/android/__init__.py
pyarmor/cli/core/android/aarch64/pyarmor_runtime.so
pyarmor/cli/core/android/aarch64/pytransform3.so
pyarmor/cli/core/android/armv7/pyarmor_runtime.so
pyarmor/cli/core/android/armv7/pytransform3.so
pyarmor/cli/core/android/x86/pyarmor_runtime.so
pyarmor/cli/core/android/x86/pytransform3.so
pyarmor/cli/core/android/x86_64/pyarmor_runtime.so
pyarmor/cli/core/android/x86_64/pytransform3.so
pyarmor_cli_core_android-7.6.8.dist-info/METADATA
pyarmor_cli_core_android-7.6.8.dist-info/WHEEL
pyarmor_cli_core_android-7.6.8.dist-info/top_level.txt
pyarmor_cli_core_android-7.6.8.dist-info/RECORD
